{
   "@context": "http://www.w3.org/ns/anno.jsonld",
   "id": "http://localhost:9999/wap/clusters/0003494_620bda0f8f8173c2c53539fb/?iris=0&page=0",
   "type": "AnnotationPage",
   "items": [
      {
         "id": "http://localhost:9999/wap/clusters/0003494_620bda0f8f8173c2c53539fb/000aa92c-35eb-4fbf-8326-54970dd99c52",
         "type": "Annotation",
         "created": "2023-11-15T20:50:34Z",
         "modified": "2023-11-15T20:50:34Z",
         "body": {
            "purpose": "linking"
         },
         "target": {
            "id": "https://api.digitale-sammlungen.de/iiif/presentation/v2/bsb00089694/canvas/352#xywh=1191,419,634,1403",
            "type": "http://iiif.io/api/presentation/3#Canvas",
            "dcterms:isPartOf": {
               "id": "https://api.digitale-sammlungen.de/iiif/presentation/v2/bsb00089694/manifest",
               "type": "http://iiif.io/api/presentation/3#Manifest",
               "label": "M+1612"
            }
         },
         "motivation": "tagging"
      },
      {
         "id": "http://localhost:9999/wap/clusters/0003494_620bda0f8f8173c2c53539fb/5efb9ac0-1e45-43b2-859a-4cabcc7d12e6",
         "type": "Annotation",
         "created": "2023-11-15T20:50:34Z",
         "modified": "2023-11-15T20:50:34Z",
         "body": {
            "purpose": "linking"
         },
         "target": {
            "id": "https://digitale.bibliothek.uni-halle.de/vd16/i3f/v20/995412/canvas/1556851#xywh=282,1085,766,1431",
            "type": "http://iiif.io/api/presentation/3#Canvas",
            "dcterms:isPartOf": {
               "id": "https://digitale.bibliothek.uni-halle.de/vd16/i3f/v20/995412/manifest",
               "type": "http://iiif.io/api/presentation/3#Manifest",
               "label": "M+1616"
            }
         },
         "motivation": "tagging"
      },
      {
         "id": "http://localhost:9999/wap/clusters/0003494_620bda0f8f8173c2c53539fb/f5f61618-4015-47b0-938b-0f2dbc56583c",
         "type": "Annotation",
         "created": "2023-11-15T20:50:34Z",
         "modified": "2023-11-15T20:50:34Z",
         "body": {
            "purpose": "linking"
         },
         "target": {
            "id": "https://www.e-rara.ch/zut/i3f/v20/2860006/canvas/2860385#xywh=238,856,598,1411",
            "type": "http://iiif.io/api/presentation/3#Canvas",
            "dcterms:isPartOf": {
               "id": "https://www.e-rara.ch/zut/i3f/v20/2860006/manifest",
               "type": "http://iiif.io/api/presentation/3#Manifest",
               "label": "M+1615"
            }
         },
         "motivation": "tagging"
      },
      {
         "id": "http://localhost:9999/wap/clusters/0003494_620bda0f8f8173c2c53539fb/6067312c-0c48-4a81-bfc7-1489bf8a9a9d",
         "type": "Annotation",
         "created": "2023-11-15T20:50:34Z",
         "modified": "2023-11-15T20:50:34Z",
         "body": {
            "purpose": "linking"
         },
         "target": {
            "id": "https://api.digitale-sammlungen.de/iiif/presentation/v2/bsb11220496/canvas/352#xywh=961,295,622,1387",
            "type": "http://iiif.io/api/presentation/3#Canvas",
            "dcterms:isPartOf": {
               "id": "https://api.digitale-sammlungen.de/iiif/presentation/v2/bsb11220496/manifest",
               "type": "http://iiif.io/api/presentation/3#Manifest",
               "label": "M+1613"
            }
         },
         "motivation": "tagging"
      },
      {
         "id": "http://localhost:9999/wap/clusters/0003494_620bda0f8f8173c2c53539fb/de9530ae-daca-45ad-8512-ec6dfd8f9760",
         "type": "Annotation",
         "created": "2023-11-15T20:50:34Z",
         "modified": "2023-11-15T20:50:34Z",
         "body": {
            "purpose": "linking"
         },
         "target": {
            "id": "https://api.digitale-sammlungen.de/iiif/presentation/v2/bsb00091089/canvas/373#xywh=246,781,682,1379",
            "type": "http://iiif.io/api/presentation/3#Canvas",
            "dcterms:isPartOf": {
               "id": "https://api.digitale-sammlungen.de/iiif/presentation/v2/bsb00091089/manifest",
               "type": "http://iiif.io/api/presentation/3#Manifest",
               "label": "M+1614"
            }
         },
         "motivation": {
            "id": "oa:tagging",
            "label": "tagging"
         }
      }
   ],
   "partOf": {
      "id": "http://localhost:9999/wap/clusters/0003494_620bda0f8f8173c2c53539fb/?iris=0",
      "modified": "2023-11-15T20:50:34Z",
      "label": "This container will contain photos of Alice.",
      "first": "http://localhost:9999/wap/clusters/0003494_620bda0f8f8173c2c53539fb/?iris=0&page=0",
      "last": "http://localhost:9999/wap/clusters/0003494_620bda0f8f8173c2c53539fb/?iris=0&page=0",
      "total": "5"
   },
   "startIndex": "0"
}