{
   "@context": "http://www.w3.org/ns/anno.jsonld",
   "id": "http://localhost:9999/wap/clusters/0005933_620bda0f8f8173c2c5354382/?iris=0&page=0",
   "type": "AnnotationPage",
   "items": [
      {
         "id": "http://localhost:9999/wap/clusters/0005933_620bda0f8f8173c2c5354382/dabc23fa-3930-4351-82bb-0ed20f367e03",
         "type": "Annotation",
         "created": "2023-11-15T21:23:40Z",
         "modified": "2023-11-15T21:23:40Z",
         "body": {
            "purpose": "linking"
         },
         "target": {
            "id": "https://iiif.onb.ac.at/presentation/ABO/Z181254106/canvas/page804#xywh=268,648,761,639",
            "type": "http://iiif.io/api/presentation/3#Canvas",
            "dcterms:isPartOf": {
               "id": "https://iiif.onb.ac.at/presentation/ABO/Z181254106/manifest",
               "type": "http://iiif.io/api/presentation/3#Manifest",
               "label": "A+2113"
            }
         },
         "motivation": "tagging"
      },
      {
         "id": "http://localhost:9999/wap/clusters/0005933_620bda0f8f8173c2c5354382/f99c2baf-b68d-42f6-8516-1c97076cd892",
         "type": "Annotation",
         "created": "2023-11-15T21:23:40Z",
         "modified": "2023-11-15T21:23:40Z",
         "body": {
            "purpose": "linking"
         },
         "target": {
            "id": "https://iiif.onb.ac.at/presentation/ABO/Z180953608/canvas/page168#xywh=328,1542,818,657",
            "type": "http://iiif.io/api/presentation/3#Canvas",
            "dcterms:isPartOf": {
               "id": "https://iiif.onb.ac.at/presentation/ABO/Z180953608/manifest"
            }
         },
         "motivation": "tagging"
      },
      {
         "id": "http://localhost:9999/wap/clusters/0005933_620bda0f8f8173c2c5354382/0cfd7cb3-6d61-42dc-8d66-a723bdbf0ae9",
         "type": "Annotation",
         "created": "2023-11-15T21:23:40Z",
         "modified": "2023-11-15T21:23:40Z",
         "body": {
            "purpose": "linking"
         },
         "target": {
            "id": "https://api.digitale-sammlungen.de/iiif/presentation/v2/bsb10149475/canvas/262#xywh=336,2097,810,675",
            "type": "http://iiif.io/api/presentation/3#Canvas",
            "dcterms:isPartOf": {
               "id": "https://api.digitale-sammlungen.de/iiif/presentation/v2/bsb10149475/manifest"
            }
         },
         "motivation": "tagging"
      },
      {
         "id": "http://localhost:9999/wap/clusters/0005933_620bda0f8f8173c2c5354382/8dc92b14-7afd-48c8-a2c4-fb4b987a4276",
         "type": "Annotation",
         "created": "2023-11-15T21:23:40Z",
         "modified": "2023-11-15T21:23:40Z",
         "body": {
            "purpose": "linking"
         },
         "target": {
            "id": "https://iiif.onb.ac.at/presentation/ABO/Z180953608/canvas/page566#xywh=1363,1720,808,665",
            "type": "http://iiif.io/api/presentation/3#Canvas",
            "dcterms:isPartOf": {
               "id": "https://iiif.onb.ac.at/presentation/ABO/Z180953608/manifest"
            }
         },
         "motivation": "tagging"
      },
      {
         "id": "http://localhost:9999/wap/clusters/0005933_620bda0f8f8173c2c5354382/aa258f1e-6076-47df-8c3a-575edbcbf9a5",
         "type": "Annotation",
         "created": "2023-11-15T21:23:40Z",
         "modified": "2023-11-15T21:23:40Z",
         "body": {
            "purpose": "linking"
         },
         "target": {
            "id": "https://api.digitale-sammlungen.de/iiif/presentation/v2/bsb10149475/canvas/7#xywh=1419,314,868,712",
            "type": "http://iiif.io/api/presentation/3#Canvas",
            "dcterms:isPartOf": {
               "id": "https://api.digitale-sammlungen.de/iiif/presentation/v2/bsb10149475/manifest"
            }
         },
         "motivation": "tagging"
      },
      {
         "id": "http://localhost:9999/wap/clusters/0005933_620bda0f8f8173c2c5354382/24ced37d-78f3-4939-bf33-ba08b6057611",
         "type": "Annotation",
         "created": "2023-11-15T21:23:40Z",
         "modified": "2023-11-15T21:23:40Z",
         "body": {
            "purpose": "linking"
         },
         "target": {
            "id": "https://api.digitale-sammlungen.de/iiif/presentation/v2/bsb10149475/canvas/296#xywh=1076,2091,849,715",
            "type": "http://iiif.io/api/presentation/3#Canvas",
            "dcterms:isPartOf": {
               "id": "https://api.digitale-sammlungen.de/iiif/presentation/v2/bsb10149475/manifest"
            }
         },
         "motivation": "tagging"
      },
      {
         "id": "http://localhost:9999/wap/clusters/0005933_620bda0f8f8173c2c5354382/80819934-d968-4af5-a119-34c2dd6266e8",
         "type": "Annotation",
         "created": "2023-11-15T21:23:40Z",
         "modified": "2023-11-15T21:23:40Z",
         "body": {
            "purpose": "linking"
         },
         "target": {
            "id": "https://iiif.onb.ac.at/presentation/ABO/Z180953608/canvas/page789#xywh=1221,550,808,663",
            "type": "http://iiif.io/api/presentation/3#Canvas",
            "dcterms:isPartOf": {
               "id": "https://iiif.onb.ac.at/presentation/ABO/Z180953608/manifest",
               "type": "http://iiif.io/api/presentation/3#Manifest",
               "label": "B+8959"
            }
         },
         "motivation": "tagging"
      },
      {
         "id": "http://localhost:9999/wap/clusters/0005933_620bda0f8f8173c2c5354382/9d843672-a05b-40b8-b317-899b070fa496",
         "type": "Annotation",
         "created": "2023-11-15T21:23:40Z",
         "modified": "2023-11-15T21:23:40Z",
         "body": {
            "purpose": "linking"
         },
         "target": {
            "id": "https://api.digitale-sammlungen.de/iiif/presentation/v2/bsb10149475/canvas/24#xywh=1494,590,806,693",
            "type": "http://iiif.io/api/presentation/3#Canvas",
            "dcterms:isPartOf": {
               "id": "https://api.digitale-sammlungen.de/iiif/presentation/v2/bsb10149475/manifest"
            }
         },
         "motivation": "tagging"
      },
      {
         "id": "http://localhost:9999/wap/clusters/0005933_620bda0f8f8173c2c5354382/a5e4da4f-48d0-4908-8ff4-14ca25130043",
         "type": "Annotation",
         "created": "2023-11-15T21:23:40Z",
         "modified": "2023-11-15T21:23:40Z",
         "body": {
            "purpose": "linking"
         },
         "target": {
            "id": "https://api.digitale-sammlungen.de/iiif/presentation/v2/bsb10149475/canvas/4#xywh=1506,518,811,669",
            "type": "http://iiif.io/api/presentation/3#Canvas",
            "dcterms:isPartOf": {
               "id": "https://api.digitale-sammlungen.de/iiif/presentation/v2/bsb10149475/manifest",
               "type": "http://iiif.io/api/presentation/3#Manifest",
               "label": "A+2111"
            }
         },
         "motivation": {
            "id": "oa:tagging",
            "label": "tagging"
         }
      }
   ],
   "partOf": {
      "id": "http://localhost:9999/wap/clusters/0005933_620bda0f8f8173c2c5354382/?iris=0",
      "modified": "2023-11-15T21:23:40Z",
      "label": "This container will contain photos of Alice.",
      "first": "http://localhost:9999/wap/clusters/0005933_620bda0f8f8173c2c5354382/?iris=0&page=0",
      "last": "http://localhost:9999/wap/clusters/0005933_620bda0f8f8173c2c5354382/?iris=0&page=0",
      "total": "9"
   },
   "startIndex": "0"
}