{
   "@context": "http://www.w3.org/ns/anno.jsonld",
   "id": "http://localhost:9999/wap/clusters/0005983_620bda0f8f8173c2c53543b4/?iris=0&page=0",
   "type": "AnnotationPage",
   "items": [
      {
         "id": "http://localhost:9999/wap/clusters/0005983_620bda0f8f8173c2c53543b4/dfc0827e-22b2-4da7-9ba8-f05d900dc5aa",
         "type": "Annotation",
         "created": "2023-11-15T21:24:10Z",
         "modified": "2023-11-15T21:24:10Z",
         "body": {
            "purpose": "linking"
         },
         "target": {
            "id": "https://iiif.onb.ac.at/presentation/ABO/Z178500500/canvas/page135#xywh=106,465,1569,1851",
            "type": "http://iiif.io/api/presentation/3#Canvas",
            "dcterms:isPartOf": {
               "id": "https://iiif.onb.ac.at/presentation/ABO/Z178500500/manifest"
            }
         },
         "motivation": "tagging"
      },
      {
         "id": "http://localhost:9999/wap/clusters/0005983_620bda0f8f8173c2c53543b4/f9918cde-aa1d-4a28-887a-4fb693332840",
         "type": "Annotation",
         "created": "2023-11-15T21:24:10Z",
         "modified": "2023-11-15T21:24:10Z",
         "body": {
            "purpose": "linking"
         },
         "target": {
            "id": "https://iiif.onb.ac.at/presentation/ABO/Z178500500/canvas/page553#xywh=375,468,1318,1407",
            "type": "http://iiif.io/api/presentation/3#Canvas",
            "dcterms:isPartOf": {
               "id": "https://iiif.onb.ac.at/presentation/ABO/Z178500500/manifest"
            }
         },
         "motivation": "tagging"
      },
      {
         "id": "http://localhost:9999/wap/clusters/0005983_620bda0f8f8173c2c53543b4/adb1cedb-cace-40f2-a0cc-9d67f6f8b6f4",
         "type": "Annotation",
         "created": "2023-11-15T21:24:10Z",
         "modified": "2023-11-15T21:24:10Z",
         "body": {
            "purpose": "linking"
         },
         "target": {
            "id": "https://iiif.onb.ac.at/presentation/ABO/Z177496902/canvas/page254#xywh=199,1062,1607,1918",
            "type": "http://iiif.io/api/presentation/3#Canvas",
            "dcterms:isPartOf": {
               "id": "https://iiif.onb.ac.at/presentation/ABO/Z177496902/manifest",
               "type": "http://iiif.io/api/presentation/3#Manifest",
               "label": "F+3334"
            }
         },
         "motivation": "tagging"
      },
      {
         "id": "http://localhost:9999/wap/clusters/0005983_620bda0f8f8173c2c53543b4/06fe1732-5440-4c88-bab6-074620e20e08",
         "type": "Annotation",
         "created": "2023-11-15T21:24:10Z",
         "modified": "2023-11-15T21:24:10Z",
         "body": {
            "purpose": "linking"
         },
         "target": {
            "id": "https://iiif.onb.ac.at/presentation/ABO/Z137141504/canvas/page238#xywh=186,291,1325,1390",
            "type": "http://iiif.io/api/presentation/3#Canvas",
            "dcterms:isPartOf": {
               "id": "https://iiif.onb.ac.at/presentation/ABO/Z137141504/manifest",
               "type": "http://iiif.io/api/presentation/3#Manifest",
               "label": "A+2302"
            }
         },
         "motivation": "tagging"
      },
      {
         "id": "http://localhost:9999/wap/clusters/0005983_620bda0f8f8173c2c53543b4/2558d513-467b-4577-89fb-8420c34c3ed9",
         "type": "Annotation",
         "created": "2023-11-15T21:24:10Z",
         "modified": "2023-11-15T21:24:10Z",
         "body": {
            "purpose": "linking"
         },
         "target": {
            "id": "https://iiif.onb.ac.at/presentation/ABO/Z178500500/canvas/page524#xywh=266,860,1600,1890",
            "type": "http://iiif.io/api/presentation/3#Canvas",
            "dcterms:isPartOf": {
               "id": "https://iiif.onb.ac.at/presentation/ABO/Z178500500/manifest"
            }
         },
         "motivation": "tagging"
      },
      {
         "id": "http://localhost:9999/wap/clusters/0005983_620bda0f8f8173c2c53543b4/c42cae82-b437-40a9-9a18-9fda93250565",
         "type": "Annotation",
         "created": "2023-11-15T21:24:10Z",
         "modified": "2023-11-15T21:24:10Z",
         "body": {
            "purpose": "linking"
         },
         "target": {
            "id": "https://iiif.onb.ac.at/presentation/ABO/Z178500500/canvas/page444#xywh=534,1722,1334,1408",
            "type": "http://iiif.io/api/presentation/3#Canvas",
            "dcterms:isPartOf": {
               "id": "https://iiif.onb.ac.at/presentation/ABO/Z178500500/manifest",
               "type": "http://iiif.io/api/presentation/3#Manifest",
               "label": "R+2539"
            }
         },
         "motivation": {
            "id": "oa:tagging",
            "label": "tagging"
         }
      }
   ],
   "partOf": {
      "id": "http://localhost:9999/wap/clusters/0005983_620bda0f8f8173c2c53543b4/?iris=0",
      "modified": "2023-11-15T21:24:10Z",
      "label": "This container will contain photos of Alice.",
      "first": "http://localhost:9999/wap/clusters/0005983_620bda0f8f8173c2c53543b4/?iris=0&page=0",
      "last": "http://localhost:9999/wap/clusters/0005983_620bda0f8f8173c2c53543b4/?iris=0&page=0",
      "total": "6"
   },
   "startIndex": "0"
}