{
   "@context": "http://www.w3.org/ns/anno.jsonld",
   "id": "http://localhost:9999/wap/clusters/0000359_620bda0f8f8173c2c5352dbc/?iris=0&page=0",
   "type": "AnnotationPage",
   "items": [
      {
         "id": "http://localhost:9999/wap/clusters/0000359_620bda0f8f8173c2c5352dbc/2bd178e8-dd16-4b67-9a06-6275c442a886",
         "type": "Annotation",
         "created": "2023-11-15T20:08:11Z",
         "modified": "2023-11-15T20:08:11Z",
         "body": {
            "purpose": "linking"
         },
         "target": {
            "id": "https://iiif.onb.ac.at/presentation/ABO/Z181419004/canvas/page60#xywh=474,2033,440,446",
            "type": "http://iiif.io/api/presentation/3#Canvas",
            "dcterms:isPartOf": {
               "id": "https://iiif.onb.ac.at/presentation/ABO/Z181419004/manifest",
               "type": "http://iiif.io/api/presentation/3#Manifest",
               "label": "D+2005"
            }
         },
         "motivation": "tagging"
      },
      {
         "id": "http://localhost:9999/wap/clusters/0000359_620bda0f8f8173c2c5352dbc/d00d37ab-fee7-4a6c-b606-8b64f3fd9ba0",
         "type": "Annotation",
         "created": "2023-11-15T20:08:11Z",
         "modified": "2023-11-15T20:08:11Z",
         "body": {
            "purpose": "linking"
         },
         "target": {
            "id": "https://digitale.bibliothek.uni-halle.de/vd16/i3f/v20/996563/canvas/1048648#xywh=875,646,448,453",
            "type": "http://iiif.io/api/presentation/3#Canvas",
            "dcterms:isPartOf": {
               "id": "https://digitale.bibliothek.uni-halle.de/vd16/i3f/v20/996563/manifest",
               "type": "http://iiif.io/api/presentation/3#Manifest",
               "label": "ZV+13003"
            }
         },
         "motivation": "tagging"
      },
      {
         "id": "http://localhost:9999/wap/clusters/0000359_620bda0f8f8173c2c5352dbc/435ff470-230f-4c8a-a807-5b649926c6d1",
         "type": "Annotation",
         "created": "2023-11-15T20:08:11Z",
         "modified": "2023-11-15T20:08:11Z",
         "body": {
            "purpose": "linking"
         },
         "target": {
            "id": "https://api.digitale-sammlungen.de/iiif/presentation/v2/bsb11200291/canvas/570#xywh=380,1597,509,515",
            "type": "http://iiif.io/api/presentation/3#Canvas",
            "dcterms:isPartOf": {
               "id": "https://api.digitale-sammlungen.de/iiif/presentation/v2/bsb11200291/manifest",
               "type": "http://iiif.io/api/presentation/3#Manifest",
               "label": "L+2417"
            }
         },
         "motivation": "tagging"
      },
      {
         "id": "http://localhost:9999/wap/clusters/0000359_620bda0f8f8173c2c5352dbc/217f3e83-d1f5-4faa-a9c4-8fe392d4feb2",
         "type": "Annotation",
         "created": "2023-11-15T20:08:11Z",
         "modified": "2023-11-15T20:08:11Z",
         "body": {
            "purpose": "linking"
         },
         "target": {
            "id": "https://iiif.onb.ac.at/presentation/ABO/Z181581105/canvas/page337#xywh=927,1303,531,539",
            "type": "http://iiif.io/api/presentation/3#Canvas",
            "dcterms:isPartOf": {
               "id": "https://iiif.onb.ac.at/presentation/ABO/Z181581105/manifest",
               "type": "http://iiif.io/api/presentation/3#Manifest",
               "label": "P+3200"
            }
         },
         "motivation": "tagging"
      },
      {
         "id": "http://localhost:9999/wap/clusters/0000359_620bda0f8f8173c2c5352dbc/328e6be6-6ae5-4c4b-a76a-41786a53cd3c",
         "type": "Annotation",
         "created": "2023-11-15T20:08:11Z",
         "modified": "2023-11-15T20:08:11Z",
         "body": {
            "purpose": "linking"
         },
         "target": {
            "id": "https://api.digitale-sammlungen.de/iiif/presentation/v2/bsb11105893/canvas/324#xywh=423,790,465,466",
            "type": "http://iiif.io/api/presentation/3#Canvas",
            "dcterms:isPartOf": {
               "id": "https://api.digitale-sammlungen.de/iiif/presentation/v2/bsb11105893/manifest",
               "type": "http://iiif.io/api/presentation/3#Manifest",
               "label": "R+579"
            }
         },
         "motivation": "tagging"
      },
      {
         "id": "http://localhost:9999/wap/clusters/0000359_620bda0f8f8173c2c5352dbc/c9250d9a-3e67-4d3a-b6ff-05a053908d71",
         "type": "Annotation",
         "created": "2023-11-15T20:08:11Z",
         "modified": "2023-11-15T20:08:11Z",
         "body": {
            "purpose": "linking"
         },
         "target": {
            "id": "https://api.digitale-sammlungen.de/iiif/presentation/v2/bsb00093172/canvas/477#xywh=120,3232,503,651",
            "type": "http://iiif.io/api/presentation/3#Canvas",
            "dcterms:isPartOf": {
               "id": "https://api.digitale-sammlungen.de/iiif/presentation/v2/bsb00093172/manifest",
               "type": "http://iiif.io/api/presentation/3#Manifest",
               "label": "L+2425"
            }
         },
         "motivation": "tagging"
      },
      {
         "id": "http://localhost:9999/wap/clusters/0000359_620bda0f8f8173c2c5352dbc/d37afa8e-9184-43bf-95d1-5fe8df32e9e3",
         "type": "Annotation",
         "created": "2023-11-15T20:08:11Z",
         "modified": "2023-11-15T20:08:11Z",
         "body": {
            "purpose": "linking"
         },
         "target": {
            "id": "https://api.digitale-sammlungen.de/iiif/presentation/v2/bsb10166478/canvas/157#xywh=83,1004,429,430",
            "type": "http://iiif.io/api/presentation/3#Canvas",
            "dcterms:isPartOf": {
               "id": "https://api.digitale-sammlungen.de/iiif/presentation/v2/bsb10166478/manifest",
               "type": "http://iiif.io/api/presentation/3#Manifest",
               "label": "R+558"
            }
         },
         "motivation": "tagging"
      },
      {
         "id": "http://localhost:9999/wap/clusters/0000359_620bda0f8f8173c2c5352dbc/8d99401d-e2ad-491b-b44a-3f881595c32b",
         "type": "Annotation",
         "created": "2023-11-15T20:08:11Z",
         "modified": "2023-11-15T20:08:11Z",
         "body": {
            "purpose": "linking"
         },
         "target": {
            "id": "https://iiif.onb.ac.at/presentation/ABO/Z197818309/canvas/page584#xywh=360,1228,444,444",
            "type": "http://iiif.io/api/presentation/3#Canvas",
            "dcterms:isPartOf": {
               "id": "https://iiif.onb.ac.at/presentation/ABO/Z197818309/manifest",
               "type": "http://iiif.io/api/presentation/3#Manifest",
               "label": "L+2420"
            }
         },
         "motivation": "tagging"
      },
      {
         "id": "http://localhost:9999/wap/clusters/0000359_620bda0f8f8173c2c5352dbc/3bf0879b-35b1-4cae-86af-d776ada03fde",
         "type": "Annotation",
         "created": "2023-11-15T20:08:11Z",
         "modified": "2023-11-15T20:08:11Z",
         "body": {
            "purpose": "linking"
         },
         "target": {
            "id": "https://iiif.onb.ac.at/presentation/ABO/Z167529105/canvas/page56#xywh=468,635,461,446",
            "type": "http://iiif.io/api/presentation/3#Canvas",
            "dcterms:isPartOf": {
               "id": "https://iiif.onb.ac.at/presentation/ABO/Z167529105/manifest",
               "type": "http://iiif.io/api/presentation/3#Manifest",
               "label": "D+2004"
            }
         },
         "motivation": "tagging"
      },
      {
         "id": "http://localhost:9999/wap/clusters/0000359_620bda0f8f8173c2c5352dbc/d034bbbb-a59b-4150-b78c-0ecc9027b54a",
         "type": "Annotation",
         "created": "2023-11-15T20:08:11Z",
         "modified": "2023-11-15T20:08:11Z",
         "body": {
            "purpose": "linking"
         },
         "target": {
            "id": "https://iiif.onb.ac.at/presentation/ABO/Z183605101/canvas/page291#xywh=1464,1057,439,441",
            "type": "http://iiif.io/api/presentation/3#Canvas",
            "dcterms:isPartOf": {
               "id": "https://iiif.onb.ac.at/presentation/ABO/Z183605101/manifest",
               "type": "http://iiif.io/api/presentation/3#Manifest",
               "label": "B+8704"
            }
         },
         "motivation": "tagging"
      },
      {
         "id": "http://localhost:9999/wap/clusters/0000359_620bda0f8f8173c2c5352dbc/b56e2a46-d283-4729-a590-0561960e7db7",
         "type": "Annotation",
         "created": "2023-11-15T20:08:11Z",
         "modified": "2023-11-15T20:08:11Z",
         "body": {
            "purpose": "linking"
         },
         "target": {
            "id": "https://api.digitale-sammlungen.de/iiif/presentation/v2/bsb00086989/canvas/477#xywh=241,2002,534,542",
            "type": "http://iiif.io/api/presentation/3#Canvas",
            "dcterms:isPartOf": {
               "id": "https://api.digitale-sammlungen.de/iiif/presentation/v2/bsb00086989/manifest",
               "type": "http://iiif.io/api/presentation/3#Manifest",
               "label": "L+2422"
            }
         },
         "motivation": "tagging"
      },
      {
         "id": "http://localhost:9999/wap/clusters/0000359_620bda0f8f8173c2c5352dbc/d7af89e0-c9f6-4df7-96f3-b8f15deeadc7",
         "type": "Annotation",
         "created": "2023-11-15T20:08:11Z",
         "modified": "2023-11-15T20:08:11Z",
         "body": {
            "purpose": "linking"
         },
         "target": {
            "id": "https://api.digitale-sammlungen.de/iiif/presentation/v2/bsb10191152/canvas/232#xywh=534,495,446,440",
            "type": "http://iiif.io/api/presentation/3#Canvas",
            "dcterms:isPartOf": {
               "id": "https://api.digitale-sammlungen.de/iiif/presentation/v2/bsb10191152/manifest",
               "type": "http://iiif.io/api/presentation/3#Manifest",
               "label": "R+560"
            }
         },
         "motivation": "tagging"
      },
      {
         "id": "http://localhost:9999/wap/clusters/0000359_620bda0f8f8173c2c5352dbc/0b99c18f-bb22-4bd8-be11-927c0539c34d",
         "type": "Annotation",
         "created": "2023-11-15T20:08:11Z",
         "modified": "2023-11-15T20:08:11Z",
         "body": {
            "purpose": "linking"
         },
         "target": {
            "id": "https://api.digitale-sammlungen.de/iiif/presentation/v2/bsb11057820/canvas/463#xywh=264,2788,451,451",
            "type": "http://iiif.io/api/presentation/3#Canvas",
            "dcterms:isPartOf": {
               "id": "https://api.digitale-sammlungen.de/iiif/presentation/v2/bsb11057820/manifest",
               "type": "http://iiif.io/api/presentation/3#Manifest",
               "label": "L+2426"
            }
         },
         "motivation": "tagging"
      },
      {
         "id": "http://localhost:9999/wap/clusters/0000359_620bda0f8f8173c2c5352dbc/1d145a41-fec5-4f3c-92dd-6e9f0ea107b8",
         "type": "Annotation",
         "created": "2023-11-15T20:08:11Z",
         "modified": "2023-11-15T20:08:11Z",
         "body": {
            "purpose": "linking"
         },
         "target": {
            "id": "https://digitale.bibliothek.uni-halle.de/vd16/i3f/v20/995453/canvas/2646036#xywh=304,1357,464,450",
            "type": "http://iiif.io/api/presentation/3#Canvas",
            "dcterms:isPartOf": {
               "id": "https://digitale.bibliothek.uni-halle.de/vd16/i3f/v20/995453/manifest",
               "type": "http://iiif.io/api/presentation/3#Manifest",
               "label": "ZV+13002"
            }
         },
         "motivation": "tagging"
      },
      {
         "id": "http://localhost:9999/wap/clusters/0000359_620bda0f8f8173c2c5352dbc/6b87c289-5787-4308-a441-9e4a3be93ffe",
         "type": "Annotation",
         "created": "2023-11-15T20:08:11Z",
         "modified": "2023-11-15T20:08:11Z",
         "body": {
            "purpose": "linking"
         },
         "target": {
            "id": "https://api.digitale-sammlungen.de/iiif/presentation/v2/bsb10191439/canvas/320#xywh=481,226,437,437",
            "type": "http://iiif.io/api/presentation/3#Canvas",
            "dcterms:isPartOf": {
               "id": "https://api.digitale-sammlungen.de/iiif/presentation/v2/bsb10191439/manifest",
               "type": "http://iiif.io/api/presentation/3#Manifest",
               "label": "R+581"
            }
         },
         "motivation": "tagging"
      },
      {
         "id": "http://localhost:9999/wap/clusters/0000359_620bda0f8f8173c2c5352dbc/ea1db04b-4e17-4fc2-87a1-a74c7fdcec29",
         "type": "Annotation",
         "created": "2023-11-15T20:08:11Z",
         "modified": "2023-11-15T20:08:11Z",
         "body": {
            "purpose": "linking"
         },
         "target": {
            "id": "https://api.digitale-sammlungen.de/iiif/presentation/v2/bsb10191149/canvas/164#xywh=473,841,449,442",
            "type": "http://iiif.io/api/presentation/3#Canvas",
            "dcterms:isPartOf": {
               "id": "https://api.digitale-sammlungen.de/iiif/presentation/v2/bsb10191149/manifest",
               "type": "http://iiif.io/api/presentation/3#Manifest",
               "label": "R+559"
            }
         },
         "motivation": {
            "id": "oa:tagging",
            "label": "tagging"
         }
      }
   ],
   "partOf": {
      "id": "http://localhost:9999/wap/clusters/0000359_620bda0f8f8173c2c5352dbc/?iris=0",
      "modified": "2023-11-15T20:08:11Z",
      "label": "This container will contain photos of Alice.",
      "first": "http://localhost:9999/wap/clusters/0000359_620bda0f8f8173c2c5352dbc/?iris=0&page=0",
      "last": "http://localhost:9999/wap/clusters/0000359_620bda0f8f8173c2c5352dbc/?iris=0&page=0",
      "total": "16"
   },
   "startIndex": "0"
}