{
   "@context": "http://www.w3.org/ns/anno.jsonld",
   "id": "http://localhost:9999/wap/clusters/0004226_620bda0f8f8173c2c5353cd7/?iris=0&page=0",
   "type": "AnnotationPage",
   "items": [
      {
         "id": "http://localhost:9999/wap/clusters/0004226_620bda0f8f8173c2c5353cd7/7b966bea-91b9-468f-b86f-5fa8b7894d68",
         "type": "Annotation",
         "created": "2023-11-15T20:59:26Z",
         "modified": "2023-11-15T20:59:26Z",
         "body": {
            "purpose": "linking"
         },
         "target": {
            "id": "https://content.staatsbibliothek-berlin.de/dc/865522138-0216/canvas#xywh=310,360,2038,3016",
            "type": "http://iiif.io/api/presentation/3#Canvas",
            "dcterms:isPartOf": {
               "id": "https://content.staatsbibliothek-berlin.de/dc/865522138/manifest",
               "type": "http://iiif.io/api/presentation/3#Manifest",
               "label": "V+1138"
            }
         },
         "motivation": "tagging"
      },
      {
         "id": "http://localhost:9999/wap/clusters/0004226_620bda0f8f8173c2c5353cd7/2dd1bb28-0eac-4acd-b069-a1c04c302d44",
         "type": "Annotation",
         "created": "2023-11-15T20:59:26Z",
         "modified": "2023-11-15T20:59:26Z",
         "body": {
            "purpose": "linking"
         },
         "target": {
            "id": "https://api.digitale-sammlungen.de/iiif/presentation/v2/bsb10146466/canvas/179#xywh=143,306,1991,2952",
            "type": "http://iiif.io/api/presentation/3#Canvas",
            "dcterms:isPartOf": {
               "id": "https://api.digitale-sammlungen.de/iiif/presentation/v2/bsb10146466/manifest",
               "type": "http://iiif.io/api/presentation/3#Manifest",
               "label": "V+1125"
            }
         },
         "motivation": "tagging"
      },
      {
         "id": "http://localhost:9999/wap/clusters/0004226_620bda0f8f8173c2c5353cd7/52345853-c11a-4ed0-af32-913dd3dbab53",
         "type": "Annotation",
         "created": "2023-11-15T20:59:26Z",
         "modified": "2023-11-15T20:59:26Z",
         "body": {
            "purpose": "linking"
         },
         "target": {
            "id": "https://api.digitale-sammlungen.de/iiif/presentation/v2/bsb10146472/canvas/511#xywh=109,232,2008,2986",
            "type": "http://iiif.io/api/presentation/3#Canvas",
            "dcterms:isPartOf": {
               "id": "https://api.digitale-sammlungen.de/iiif/presentation/v2/bsb10146472/manifest",
               "type": "http://iiif.io/api/presentation/3#Manifest",
               "label": "V+1139"
            }
         },
         "motivation": "tagging"
      },
      {
         "id": "http://localhost:9999/wap/clusters/0004226_620bda0f8f8173c2c5353cd7/5fd08f36-da41-4ff2-9f15-937577805165",
         "type": "Annotation",
         "created": "2023-11-15T20:59:26Z",
         "modified": "2023-11-15T20:59:26Z",
         "body": {
            "purpose": "linking"
         },
         "target": {
            "id": "https://api.digitale-sammlungen.de/iiif/presentation/v2/bsb10146470/canvas/212#xywh=206,250,1958,2945",
            "type": "http://iiif.io/api/presentation/3#Canvas",
            "dcterms:isPartOf": {
               "id": "https://api.digitale-sammlungen.de/iiif/presentation/v2/bsb10146470/manifest",
               "type": "http://iiif.io/api/presentation/3#Manifest",
               "label": "V+1137"
            }
         },
         "motivation": "tagging"
      },
      {
         "id": "http://localhost:9999/wap/clusters/0004226_620bda0f8f8173c2c5353cd7/9e519b48-d49a-421b-8059-b4c1a15fab23",
         "type": "Annotation",
         "created": "2023-11-15T20:59:26Z",
         "modified": "2023-11-15T20:59:26Z",
         "body": {
            "purpose": "linking"
         },
         "target": {
            "id": "https://api.digitale-sammlungen.de/iiif/presentation/v2/bsb10146473/canvas/535#xywh=99,210,1909,2868",
            "type": "http://iiif.io/api/presentation/3#Canvas",
            "dcterms:isPartOf": {
               "id": "https://api.digitale-sammlungen.de/iiif/presentation/v2/bsb10146473/manifest",
               "type": "http://iiif.io/api/presentation/3#Manifest",
               "label": "V+1140"
            }
         },
         "motivation": {
            "id": "oa:tagging",
            "label": "tagging"
         }
      }
   ],
   "partOf": {
      "id": "http://localhost:9999/wap/clusters/0004226_620bda0f8f8173c2c5353cd7/?iris=0",
      "modified": "2023-11-15T20:59:26Z",
      "label": "This container will contain photos of Alice.",
      "first": "http://localhost:9999/wap/clusters/0004226_620bda0f8f8173c2c5353cd7/?iris=0&page=0",
      "last": "http://localhost:9999/wap/clusters/0004226_620bda0f8f8173c2c5353cd7/?iris=0&page=0",
      "total": "5"
   },
   "startIndex": "0"
}